Workbook

Sheet Custo consolidado
A1: NOTA 15 | Custo dos intangíveis — Consolidado 2025
A3: Movimentação | B3: Software | C3: Marcas e patentes | D3: Carteira de clientes | E3: Ativos de desenvolvimento | F3: Direito de uso de licenças | G3: Outros | H3: Goodwill | I3: Total (R$ mil)
A4: Saldo 2024 | B4: 989118 | C4: 143707 | D4: 806276 | E4: 167654 | F4: 0 | G4: 83627 | H4: 3381795 | I4: =SUM(B4:H4) -> 5572177
A5: Adições | B5: 27633 | C5: 9941 | D5: 2580 | E5: 67611 | F5: 20834 | G5: 0 | H5: 0 | I5: =SUM(B5:H5) -> 128599
A6: Combinação de negócios | B6: 94 | C6: 63 | D6: 0 | E6: -345 | F6: 0 | G6: -917 | H6: 8180 | I6: =SUM(B6:H6) -> 7075
A7: Variação cambial | B7: -95 | C7: 0 | D7: 0 | E7: 0 | F7: 0 | G7: 0 | H7: 0 | I7: =SUM(B7:H7) -> -95
A8: Baixas | B8: 0 | C8: 0 | D8: -277 | E8: -3056 | F8: 0 | G8: 0 | H8: 0 | I8: =SUM(B8:H8) -> -3333
A9: Ativo mantido para venda | B9: -37076 | C9: 0 | D9: -71725 | E9: -8200 | F9: 0 | G9: -1373 | H9: -222836 | I9: =SUM(B9:H9) -> -341210
A10: Saldo 2025 | B10: 979674 | C10: 153711 | D10: 736854 | E10: 223664 | F10: 20834 | G10: 81337 | H10: 3167139 | I10: =SUM(B10:H10) -> 5363213
A12: Diferença: saldo informado menos movimentação | B12: =B10-SUM(B4:B9) -> 0 | C12: =C10-SUM(C4:C9) -> 0 | D12: =D10-SUM(D4:D9) -> 0 | E12: =E10-SUM(E4:E9) -> 0 | F12: =F10-SUM(F4:F9) -> 0 | G12: =G10-SUM(G4:G9) -> 0 | H12: =H10-SUM(H4:H9) -> 0 | I12: =I10-SUM(I4:I9) -> 0
A14: Fonte: DFP TOTVS 2025, Nota 15, página 51 de 76 (consolidado), valores em R$ mil.

Sheet Amortização
A1: NOTA 15 | Amortização acumulada — Consolidado 2025
A3: Movimentação | B3: Software | C3: Marcas e patentes | D3: Carteira de clientes | E3: Ativos de desenvolvimento | F3: Direito de uso de licenças | G3: Outros | H3: Goodwill | I3: Total (R$ mil)
A4: Saldo 2024 | B4: -627588 | C4: -101445 | D4: -469830 | E4: -49692 | F4: 0 | G4: -62397 | H4: 0 | I4: =SUM(B4:H4) -> -1310952
A5: Amortização do exercício | B5: -75812 | C5: -5471 | D5: -64042 | E5: -19816 | F5: -3906 | G5: -4367 | H5: 0 | I5: =SUM(B5:H5) -> -173414
A6: Combinação de negócios | B6: 0 | C6: -1 | D6: 0 | E6: -5 | F6: 0 | G6: 0 | H6: 0 | I6: =SUM(B6:H6) -> -6
A7: Variação cambial | B7: 76 | C7: 0 | D7: 0 | E7: 0 | F7: 0 | G7: 0 | H7: 0 | I7: =SUM(B7:H7) -> 76
A8: Baixas | B8: 0 | C8: 0 | D8: 142 | E8: 616 | F8: 0 | G8: 0 | H8: 0 | I8: =SUM(B8:H8) -> 758
A9: Ativo mantido para venda | B9: 13505 | C9: 0 | D9: 7865 | E9: 2625 | F9: 0 | G9: 583 | H9: 0 | I9: =SUM(B9:H9) -> 24578
A10: Saldo 2025 | B10: -689819 | C10: -106917 | D10: -525865 | E10: -66272 | F10: -3906 | G10: -66181 | H10: 0 | I10: =SUM(B10:H10) -> -1458960
A12: Diferença: saldo informado menos movimentação | B12: =B10-SUM(B4:B9) -> 0 | C12: =C10-SUM(C4:C9) -> 0 | D12: =D10-SUM(D4:D9) -> 0 | E12: =E10-SUM(E4:E9) -> 0 | F12: =F10-SUM(F4:F9) -> 0 | G12: =G10-SUM(G4:G9) -> 0 | H12: =H10-SUM(H4:H9) -> 0 | I12: =I10-SUM(I4:I9) -> 0
A14: Fonte: DFP TOTVS 2025, Nota 15, página 51 de 76. Amortização expressa com sinal negativo.

Sheet Conciliação
A1: CONCILIAÇÃO | Saldos líquidos de intangíveis 2024–2025
A3: Indicador | B3: Software | C3: Marcas e patentes | D3: Carteira de clientes | E3: Ativos de desenvolvimento | F3: Direito de uso de licenças | G3: Outros | H3: Goodwill | I3: Total (R$ mil)
A4: Custo 2024 | B4: ='Custo consolidado'!B4 -> 989118 | C4: ='Custo consolidado'!C4 -> 143707 | D4: ='Custo consolidado'!D4 -> 806276 | E4: ='Custo consolidado'!E4 -> 167654 | F4: ='Custo consolidado'!F4 -> 0 | G4: ='Custo consolidado'!G4 -> 83627 | H4: ='Custo consolidado'!H4 -> 3381795 | I4: ='Custo consolidado'!I4 -> 5572177
A5: Amortização 2024 | B5: =Amortização!B4 -> -627588 | C5: =Amortização!C4 -> -101445 | D5: =Amortização!D4 -> -469830 | E5: =Amortização!E4 -> -49692 | F5: =Amortização!F4 -> 0 | G5: =Amortização!G4 -> -62397 | H5: =Amortização!H4 -> 0 | I5: =Amortização!I4 -> -1310952
A6: Líquido 2024 (calculado) | B6: =B4+B5 -> 361530 | C6: =C4+C5 -> 42262 | D6: =D4+D5 -> 336446 | E6: =E4+E5 -> 117962 | F6: =F4+F5 -> 0 | G6: =G4+G5 -> 21230 | H6: =H4+H5 -> 3381795 | I6: =I4+I5 -> 4261225
A7: Líquido 2024 (publicado) | B7: 361530 | C7: 42262 | D7: 336446 | E7: 117962 | F7: 0 | G7: 21230 | H7: 3381795 | I7: =SUM(B7:H7) -> 4261225
A8: Diferença 2024 | B8: =B6-B7 -> 0 | C8: =C6-C7 -> 0 | D8: =D6-D7 -> 0 | E8: =E6-E7 -> 0 | F8: =F6-F7 -> 0 | G8: =G6-G7 -> 0 | H8: =H6-H7 -> 0 | I8: =I6-I7 -> 0
A9: Custo 2025 | B9: ='Custo consolidado'!B10 -> 979674 | C9: ='Custo consolidado'!C10 -> 153711 | D9: ='Custo consolidado'!D10 -> 736854 | E9: ='Custo consolidado'!E10 -> 223664 | F9: ='Custo consolidado'!F10 -> 20834 | G9: ='Custo consolidado'!G10 -> 81337 | H9: ='Custo consolidado'!H10 -> 3167139 | I9: ='Custo consolidado'!I10 -> 5363213
A10: Amortização 2025 | B10: =Amortização!B10 -> -689819 | C10: =Amortização!C10 -> -106917 | D10: =Amortização!D10 -> -525865 | E10: =Amortização!E10 -> -66272 | F10: =Amortização!F10 -> -3906 | G10: =Amortização!G10 -> -66181 | H10: =Amortização!H10 -> 0 | I10: =Amortização!I10 -> -1458960
A11: Líquido 2025 (calculado) | B11: =B9+B10 -> 289855 | C11: =C9+C10 -> 46794 | D11: =D9+D10 -> 210989 | E11: =E9+E10 -> 157392 | F11: =F9+F10 -> 16928 | G11: =G9+G10 -> 15156 | H11: =H9+H10 -> 3167139 | I11: =I9+I10 -> 3904253
A12: Líquido 2025 (publicado) | B12: 289855 | C12: 46794 | D12: 210989 | E12: 157392 | F12: 16928 | G12: 15156 | H12: 3167139 | I12: =SUM(B12:H12) -> 3904253
A13: Diferença 2025 | B13: =B11-B12 -> 0 | C13: =C11-C12 -> 0 | D13: =D11-D12 -> 0 | E13: =E11-E12 -> 0 | F13: =F11-F12 -> 0 | G13: =G11-G12 -> 0 | H13: =H11-H12 -> 0 | I13: =I11-I12 -> 0
A14: Variação líquida 2025 vs 2024 | B14: =B11-B6 -> -71675 | C14: =C11-C6 -> 4532 | D14: =D11-D6 -> -125457 | E14: =E11-E6 -> 39430 | F14: =F11-F6 -> 16928 | G14: =G11-G6 -> -6074 | H14: =H11-H6 -> -214656 | I14: =I11-I6 -> -356972
A15: Variação percentual | B15: =IFERROR(B14/B6,0) -> -0.19825464 | C15: =IFERROR(C14/C6,0) -> 0.10723581 | D15: =IFERROR(D14/D6,0) -> -0.37288896 | E15: =IFERROR(E14/E6,0) -> 0.33426019 | F15: =IFERROR(F14/F6,0) -> 0 | G15: =IFERROR(G14/G6,0) -> -0.28610457 | H15: =IFERROR(H14/H6,0) -> -0.063473983 | I15: =IFERROR(I14/I6,0) -> -0.083772155
A17: Conclusão: diferenças de reconciliação esperadas iguais a zero. A conciliação é apenas dos valores públicos, não de registros analíticos reais.
A18: Nota: as movimentações incluem reclassificação para ativos mantidos para venda, que afeta custo e amortização acumulada.

Sheet Goodwill por UGC
A1: NOTA 15.1 | Goodwill por UGC e principais movimentos
A3: UGC | B3: Saldo 2024 | C3: Combinações 2025 | D3: Mantido para venda | E3: Saldo 2025
A4: Gestão | B4: 1376449 | C4: 8180 | D4: -43373 | E4: 1341256
A5: Dimensa | B5: 179463 | C5: 0 | D5: -179463 | E5: 0
A6: RD | B6: 1825883 | C6: 0 | D6: 0 | E6: 1825883
A7: Total | B7: =SUM(B4:B6) -> 3381795 | C7: =SUM(C4:C6) -> 8180 | D7: =SUM(D4:D6) -> -222836 | E7: =SUM(E4:E6) -> 3167139
A9: Referência: Nota 15.1, pág. 52 de 76. Goodwill não é amortizado; avaliar recuperabilidade por UGC.

Sheet Instruções e fontes
A1: CONCILIAÇÃO DOS INTANGÍVEIS — TOTVS S.A. (2025)
A2: Natureza | B2: Conciliação documental com base em informações públicas. Não representa auditoria de razão analítico.
A3: Unidade | B3: Todos os valores monetários em milhares de reais (R$ mil).
A4: Escopo | B4: Demonstrações CONSOLIDADAS; 2024 comparativo e 2025 exercício-base.
A5: Fonte | B5: TOTVS S.A. DFP 31/12/2025 — Notas Explicativas, Nota 15, páginas 49–53 de 76.
A6: Link | B6: https://www.rad.cvm.gov.br/
A7: Arquivos | B7: DFP TOTVS 2025 e notas explicativas anexadas pelo usuário.
A8: Lógica | B8: Saldo final = saldo inicial + adições + combinações + câmbio + baixas + reclassificações; custo e amortização segregados.
A9: Sinal | B9: Amortização acumulada negativa; movimentos positivos representam reversões/baixas da amortização.
A10: Controle | B10: As colunas Diferença 2024 e Diferença 2025 devem apresentar zero em todas as classes.
A11: Goodwill | B11: Não sujeito à amortização; analisado por unidades geradoras de caixa.
A12: Limitação | B12: Os dados publicados não permitem verificar individualmente ativos, documentos de suporte ou testes de impairment.
A13: Próximo passo | B13: Usar saldos por classe como controle da futura base SINTÉTICA de 500.000 registros.
A14: Preparador | B14: Matrícula 241021687 — trabalho acadêmico, sem revisão profissional simulada.
