Workbook

Sheet BP_Ativo
A1: BP Ativo | TOTVS consolidado
A2: DFP TOTVS S.A. 31/12/2025, versão 1, consolidado (R$ mil)
A4: Código CVM | B4: Descrição da conta | C4: 2025 (R$ mil) | D4: 2024 (R$ mil) | E4: Variação R$ mil | F4: Variação %
A5: 1 | B5: Ativo Total | C5: 9452171 | D5: 8531721 | E5: =C5-D5 -> 920450 | F5: =IF(D5=0,"",C5/D5-1) -> 0.10788562
A6: 1.01 | B6: Ativo Circulante | C6: 3875770 | D6: 2763558 | E6: =C6-D6 -> 1112212 | F6: =IF(D6=0,"",C6/D6-1) -> 0.40245654
A7: 1.01.01 | B7: Caixa e Equivalentes de Caixa | C7: 1785703 | D7: 1942162 | E7: =C7-D7 -> -156459 | F7: =IF(D7=0,"",C7/D7-1) -> -0.080559191
A8: 1.01.03 | B8: Contas a Receber | C8: 639136 | D8: 563328 | E8: =C8-D8 -> 75808 | F8: =IF(D8=0,"",C8/D8-1) -> 0.13457169
A9: 1.01.03.01 | B9: Clientes | C9: 639136 | D9: 563328 | E9: =C9-D9 -> 75808 | F9: =IF(D9=0,"",C9/D9-1) -> 0.13457169
A10: 1.01.06 | B10: Tributos a Recuperar | C10: 53840 | D10: 83519 | E10: =C10-D10 -> -29679 | F10: =IF(D10=0,"",C10/D10-1) -> -0.35535627
A11: 1.01.06.01 | B11: Tributos Correntes a Recuperar | C11: 53840 | D11: 83519 | E11: =C11-D11 -> -29679 | F11: =IF(D11=0,"",C11/D11-1) -> -0.35535627
A12: 1.01.08 | B12: Outros Ativos Circulantes | C12: 1397091 | D12: 174549 | E12: =C12-D12 -> 1222542 | F12: =IF(D12=0,"",C12/D12-1) -> 7.0040046
A13: 1.01.08.01 | B13: Ativos Não-Correntes a Venda | C13: 1126110 | D13: 0 | E13: =C13-D13 -> 1126110 | F13: =IF(D13=0,"",C13/D13-1)
A14: 1.01.08.03 | B14: Outros | C14: 270981 | D14: 174549 | E14: =C14-D14 -> 96432 | F14: =IF(D14=0,"",C14/D14-1) -> 0.55246378
A15: 1.02 | B15: Ativo Não Circulante | C15: 5576401 | D15: 5768163 | E15: =C15-D15 -> -191762 | F15: =IF(D15=0,"",C15/D15-1) -> -0.0332449
A16: 1.02.01 | B16: Ativo Realizável a Longo Prazo | C16: 828204 | D16: 785927 | E16: =C16-D16 -> 42277 | F16: =IF(D16=0,"",C16/D16-1) -> 0.053792528
... A28: 1.02.04.02 | B28: Goodwill | C28: 3167139 | D28: 3381795 | E28: =C28-D28 -> -214656 | F28: =IF(D28=0,"",C28/D28-1) -> -0.063473983

Sheet BP_Passivo
A1: BP Passivo | TOTVS consolidado
A2: DFP TOTVS S.A. 31/12/2025, versão 1, consolidado (R$ mil)
A4: Código CVM | B4: Descrição da conta | C4: 2025 (R$ mil) | D4: 2024 (R$ mil) | E4: Variação R$ mil | F4: Variação %
A5: 2 | B5: Passivo Total | C5: 9452171 | D5: 8531721 | E5: =C5-D5 -> 920450 | F5: =IF(D5=0,"",C5/D5-1) -> 0.10788562
A6: 2.01 | B6: Passivo Circulante | C6: 1978222 | D6: 1144197 | E6: =C6-D6 -> 834025 | F6: =IF(D6=0,"",C6/D6-1) -> 0.72891731
A7: 2.01.01 | B7: Obrigações Sociais e Trabalhistas | C7: 462060 | D7: 438679 | E7: =C7-D7 -> 23381 | F7: =IF(D7=0,"",C7/D7-1) -> 0.053298653
A8: 2.01.01.01 | B8: Obrigações Sociais | C8: 49424 | D8: 42562 | E8: =C8-D8 -> 6862 | F8: =IF(D8=0,"",C8/D8-1) -> 0.16122363
A9: 2.01.01.02 | B9: Obrigações Trabalhistas | C9: 412636 | D9: 396117 | E9: =C9-D9 -> 16519 | F9: =IF(D9=0,"",C9/D9-1) -> 0.041702325
A10: 2.01.02 | B10: Fornecedores | C10: 220761 | D10: 211971 | E10: =C10-D10 -> 8790 | F10: =IF(D10=0,"",C10/D10-1) -> 0.041467937
A11: 2.01.02.01 | B11: Fornecedores Nacionais | C11: 207968 | D11: 208953 | E11: =C11-D11 -> -985 | F11: =IF(D11=0,"",C11/D11-1) -> -0.0047139787
A12: 2.01.02.02 | B12: Fornecedores Estrangeiros | C12: 12793 | D12: 3018 | E12: =C12-D12 -> 9775 | F12: =IF(D12=0,"",C12/D12-1) -> 3.2388999
A13: 2.01.03 | B13: Obrigações Fiscais | C13: 133820 | D13: 122612 | E13: =C13-D13 -> 11208 | F13: =IF(D13=0,"",C13/D13-1) -> 0.091410302
A14: 2.01.03.01 | B14: Obrigações Fiscais Federais | C14: 117918 | D14: 107846 | E14: =C14-D14 -> 10072 | F14: =IF(D14=0,"",C14/D14-1) -> 0.09339243
A15: 2.01.03.02 | B15: Obrigações Fiscais Estaduais | C15: 495 | D15: 831 | E15: =C15-D15 -> -336 | F15: =IF(D15=0,"",C15/D15-1) -> -0.40433213
A16: 2.01.03.03 | B16: Obrigações Fiscais Municipais | C16: 15407 | D16: 13935 | E16: =C16-D16 -> 1472 | F16: =IF(D16=0,"",C16/D16-1) -> 0.1056333
... A48: 2.03.09 | B48: Participação dos Acionistas Não Controladores | C48: 338177 | D48: 305769 | E48: =C48-D48 -> 32408 | F48: =IF(D48=0,"",C48/D48-1) -> 0.10598851

Sheet DRE
A1: DRE | TOTVS consolidado
A2: DFP TOTVS S.A. 31/12/2025, versão 1, consolidado (R$ mil)
A4: Código CVM | B4: Descrição da conta | C4: 2025 (R$ mil) | D4: 2024 (R$ mil) | E4: Variação R$ mil | F4: Variação %
A5: 3.01 | B5: Receita de Venda de Bens e/ou Serviços | C5: 5771867 | D5: 4914747 | E5: =C5-D5 -> 857120 | F5: =IF(D5=0,"",C5/D5-1) -> 0.17439758
A6: 3.01.01 | B6: Softwares | C6: 5771867 | D6: 4914747 | E6: =C6-D6 -> 857120 | F6: =IF(D6=0,"",C6/D6-1) -> 0.17439758
A7: 3.02 | B7: Custo dos Bens e/ou Serviços Vendidos | C7: -1716326 | D7: -1458672 | E7: =C7-D7 -> -257654 | F7: =IF(D7=0,"",C7/D7-1) -> 0.17663601
A8: 3.02.01 | B8: Custo de Softwares | C8: -1716326 | D8: -1458672 | E8: =C8-D8 -> -257654 | F8: =IF(D8=0,"",C8/D8-1) -> 0.17663601
A9: 3.03 | B9: Resultado Bruto | C9: 4055541 | D9: 3456075 | E9: =C9-D9 -> 599466 | F9: =IF(D9=0,"",C9/D9-1) -> 0.17345283
A10: 3.04 | B10: Despesas/Receitas Operacionais | C10: -2932813 | D10: -2604092 | E10: =C10-D10 -> -328721 | F10: =IF(D10=0,"",C10/D10-1) -> 0.12623248
A11: 3.04.01 | B11: Despesas com Vendas | C11: -1300048 | D11: -1114656 | E11: =C11-D11 -> -185392 | F11: =IF(D11=0,"",C11/D11-1) -> 0.16632217
A12: 3.04.02 | B12: Despesas Gerais e Administrativas | C12: -584717 | D12: -537922 | E12: =C12-D12 -> -46795 | F12: =IF(D12=0,"",C12/D12-1) -> 0.086992166
A13: 3.04.05 | B13: Outras Despesas Operacionais | C13: -1059471 | D13: -949943 | E13: =C13-D13 -> -109528 | F13: =IF(D13=0,"",C13/D13-1) -> 0.11529955
A14: 3.04.05.01 | B14: Pesquisa e Desenvolvimento | C14: -1005236 | D14: -877330 | E14: =C14-D14 -> -127906 | F14: =IF(D14=0,"",C14/D14-1) -> 0.14579007
A15: 3.04.05.03 | B15: Provisão para perda esperada | C15: -59622 | D15: -54669 | E15: =C15-D15 -> -4953 | F15: =IF(D15=0,"",C15/D15-1) -> 0.090599791
A16: 3.04.05.04 | B16: Outras Despesas/Receitas Op. Líq. | C16: 5387 | D16: -17944 | E16: =C16-D16 -> 23331 | F16: =IF(D16=0,"",C16/D16-1) -> -1.3002118
... A34: 3.11.02 | B34: Atribuído a Sócios Não Controladores | C34: 29001 | D34: 17930 | E34: =C34-D34 -> 11071 | F34: =IF(D34=0,"",C34/D34-1) -> 0.61745678

Sheet DRA
A1: DRA | TOTVS consolidado
A2: DFP TOTVS S.A. 31/12/2025, versão 1, consolidado (R$ mil)
A4: Código CVM | B4: Descrição da conta | C4: 2025 (R$ mil) | D4: 2024 (R$ mil) | E4: Variação R$ mil | F4: Variação %
A5: 4.01 | B5: Lucro Líquido Consolidado do Período | C5: 920742 | D5: 735443 | E5: =C5-D5 -> 185299 | F5: =IF(D5=0,"",C5/D5-1) -> 0.25195562
A6: 4.02 | B6: Outros Resultados Abrangentes | C6: -10617 | D6: 34241 | E6: =C6-D6 -> -44858 | F6: =IF(D6=0,"",C6/D6-1) -> -1.3100669
A7: 4.02.01 | B7: Ajuste acumulado de conversão de moeda estrangeira | C7: -10981 | D7: 34617 | E7: =C7-D7 -> -45598 | F7: =IF(D7=0,"",C7/D7-1) -> -1.3172141
A8: 4.02.02 | B8: (Perda) Ganho atuarial | C8: 364 | D8: -376 | E8: =C8-D8 -> 740 | F8: =IF(D8=0,"",C8/D8-1) -> -1.9680851
A9: 4.03 | B9: Resultado Abrangente Consolidado do Período | C9: 910125 | D9: 769684 | E9: =C9-D9 -> 140441 | F9: =IF(D9=0,"",C9/D9-1) -> 0.18246579
A10: 4.03.01 | B10: Atribuído a Sócios da Empresa Controladora | C10: 881124 | D10: 751754 | E10: =C10-D10 -> 129370 | F10: =IF(D10=0,"",C10/D10-1) -> 0.17209087
A11: 4.03.02 | B11: Atribuído a Sócios Não Controladores | C11: 29001 | D11: 17930 | E11: =C11-D11 -> 11071 | F11: =IF(D11=0,"",C11/D11-1) -> 0.61745678

Sheet DFC
A1: DFC | TOTVS consolidado
A2: DFP TOTVS S.A. 31/12/2025, versão 1, consolidado (R$ mil)
A4: Código CVM | B4: Descrição da conta | C4: 2025 (R$ mil) | D4: 2024 (R$ mil) | E4: Variação R$ mil | F4: Variação %
A5: 6.01 | B5: Caixa Líquido Atividades Operacionais | C5: 1203183 | D5: 1032985 | E5: =C5-D5 -> 170198 | F5: =IF(D5=0,"",C5/D5-1) -> 0.16476328
A6: 6.01.01 | B6: Caixa Gerado nas Operações | C6: 1842463 | D6: 1437188 | E6: =C6-D6 -> 405275 | F6: =IF(D6=0,"",C6/D6-1) -> 0.28199164
A7: 6.01.01.01 | B7: Lucro antes da tributação do imposto de renda e contribuição social | C7: 1041978 | D7: 759433 | E7: =C7-D7 -> 282545 | F7: =IF(D7=0,"",C7/D7-1) -> 0.3720473
A8: 6.01.01.02 | B8: Depreciação e Amortização | C8: 341084 | D8: 313263 | E8: =C8-D8 -> 27821 | F8: =IF(D8=0,"",C8/D8-1) -> 0.088810361
A9: 6.01.01.03 | B9: Pagamento Baseado em Ações | C9: 82603 | D9: 46390 | E9: =C9-D9 -> 36213 | F9: =IF(D9=0,"",C9/D9-1) -> 0.78062082
A10: 6.01.01.04 | B10: Perda (Ganho) na baixa de Ativos | C10: -5041 | D10: -9612 | E10: =C10-D10 -> 4571 | F10: =IF(D10=0,"",C10/D10-1) -> -0.47555139
A11: 6.01.01.05 | B11: Provisão para perda esperada | C11: 59622 | D11: 54669 | E11: =C11-D11 -> 4953 | F11: =IF(D11=0,"",C11/D11-1) -> 0.090599791
A12: 6.01.01.06 | B12: Equivalência patrimonial | C12: -11423 | D12: 1571 | E12: =C12-D12 -> -12994 | F12: =IF(D12=0,"",C12/D12-1) -> -8.2711649
A13: 6.01.01.07 | B13: Provisão para contingências | C13: 37495 | D13: 19977 | E13: =C13-D13 -> 17518 | F13: =IF(D13=0,"",C13/D13-1) -> 0.87690844
A14: 6.01.01.08 | B14: (Reversão) Provisão de outras obrigações e outros | C14: 14005 | D14: -6450 | E14: =C14-D14 -> 20455 | F14: =IF(D14=0,"",C14/D14-1) -> -3.1713178
A15: 6.01.01.10 | B15: Juros e Variações Cambiais e Monetárias, Líquidos | C15: 282140 | D15: 257947 | E15: =C15-D15 -> 24193 | F15: =IF(D15=0,"",C15/D15-1) -> 0.093790585
A16: 6.01.02 | B16: Variações nos Ativos e Passivos | C16: -291052 | D16: -78516 | E16: =C16-D16 -> -212536 | F16: =IF(D16=0,"",C16/D16-1) -> 2.7069132
... A51: 6.05.02 | B51: Saldo Final de Caixa e Equivalentes | C51: 1785703 | D51: 1942162 | E51: =C51-D51 -> -156459 | F51: =IF(D51=0,"",C51/D51-1) -> -0.080559191

Sheet DMPL_2025
A1: DMPL 2025 | TOTVS consolidado
A2: DFP TOTVS S.A. 31/12/2025, versão 1, consolidado (R$ mil)
A4: Código CVM | B4: Movimentação | C4: Capital social | D4: Reserva de capital | E4: Reserva de lucros | F4: Lucros acumulados | G4: Outros abrangentes | H4: PL controladora | I4: Não controladores | J4: PL consolidado
A5: 5.01 | B5: Saldos Iniciais | C5: 2962585 | D5: -68362 | E5: 1715436 | F5: 0 | G5: 71693 | H5: 4681352 | I5: 305769 | J5: 4987121
A6: 5.02 | B6: Ajustes de Exercícios Anteriores | C6: 0 | D6: 0 | E6: 0 | F6: 0 | G6: 0 | H6: 0 | I6: 0 | J6: 0
A7: 5.03 | B7: Saldos Iniciais Ajustados | C7: 2962585 | D7: -68362 | E7: 1715436 | F7: 0 | G7: 71693 | H7: 4681352 | I7: 305769 | J7: 4987121
A8: 5.04 | B8: Transações de Capital com os Sócios | C8: 0 | D8: -98983 | E8: 0 | F8: -358213 | G8: 0 | H8: -457196 | I8: 3407 | J8: -453789
A9: 5.04.07 | B9: Juros sobre Capital Próprio | C9: 0 | D9: 0 | E9: 0 | F9: -358213 | G9: 0 | H9: -358213 | I9: 0 | J9: -358213
A10: 5.04.08 | B10: Plano de outorga de ações | C10: 0 | D10: 71184 | E10: 0 | F10: 0 | G10: 0 | H10: 71184 | I10: 0 | J10: 71184
A11: 5.04.14 | B11: Reversão de dividendos e JSCP | C11: 0 | D11: 0 | E11: 0 | F11: 0 | G11: 0 | H11: 0 | I11: 3407 | J11: 3407
A12: 5.04.16 | B12: Opção de compra de participação de não | C12: 0 | D12: -170167 | E12: 0 | F12: 0 | G12: 0 | H12: -170167 | I12: 0 | J12: -170167
A13: 5.05 | B13: Resultado Abrangente Total | C13: 0 | D13: 0 | E13: 0 | F13: 891741 | G13: -10617 | H13: 881124 | I13: 29001 | J13: 910125
A14: 5.05.01 | B14: Lucro Líquido do Período | C14: 0 | D14: 0 | E14: 0 | F14: 891741 | G14: 0 | H14: 891741 | I14: 29001 | J14: 920742
A15: 5.05.02 | B15: Outros Resultados Abrangentes | C15: 0 | D15: 0 | E15: 0 | F15: 0 | G15: -10617 | H15: -10617 | I15: 0 | J15: -10617
A16: 5.05.02.04 | B16: Ajustes de Conversão do Período | C16: 0 | D16: 0 | E16: 0 | F16: 0 | G16: -10981 | H16: -10981 | I16: 0 | J16: -10981
... A20: 5.07 | B20: Saldos Finais | C20: 2962585 | D20: -167345 | E20: 2248964 | F20: 0 | G20: 61076 | H20: 5105280 | I20: 338177 | J20: 5443457

Sheet DMPL_2024
A1: DMPL 2024 | TOTVS consolidado
A2: DFP TOTVS S.A. 31/12/2025, versão 1, consolidado (R$ mil)
A4: Código CVM | B4: Movimentação | C4: Capital social | D4: Reserva de capital | E4: Reserva de lucros | F4: Lucros acumulados | G4: Outros abrangentes | H4: PL controladora | I4: Não controladores | J4: PL consolidado
A5: 5.01 | B5: Saldos Iniciais | C5: 2962585 | D5: 454848 | E5: 1262719 | F5: 0 | G5: 40422 | H5: 4720574 | I5: 292097 | J5: 5012671
A6: 5.02 | B6: Ajustes de Exercícios Anteriores | C6: 0 | D6: 0 | E6: 0 | F6: 0 | G6: 0 | H6: 0 | I6: 0 | J6: 0
A7: 5.03 | B7: Saldos Iniciais Ajustados | C7: 2962585 | D7: 454848 | E7: 1262719 | F7: 0 | G7: 40422 | H7: 4720574 | I7: 292097 | J7: 5012671
A8: 5.04 | B8: Transações de Capital com os Sócios | C8: 0 | D8: -523210 | E8: 911 | F8: -265707 | G8: 0 | H8: -788006 | I8: -4258 | J8: -792264
A9: 5.04.04 | B9: Ações em Tesouraria Adquiridas | C9: 0 | D9: -571368 | E9: 0 | F9: 0 | G9: 0 | H9: -571368 | I9: 0 | J9: -571368
A10: 5.04.07 | B10: Juros sobre Capital Próprio | C10: 0 | D10: 0 | E10: 0 | F10: -265707 | G10: 0 | H10: -265707 | I10: 0 | J10: -265707
A11: 5.04.08 | B11: Plano de outorga de ações | C11: 0 | D11: 48158 | E11: 0 | F11: 0 | G11: 0 | H11: 48158 | I11: 0 | J11: 48158
A12: 5.04.13 | B12: Participação de não controladores | C12: 0 | D12: 0 | E12: 0 | F12: 0 | G12: 0 | H12: 0 | I12: -4258 | J12: -4258
A13: 5.04.14 | B13: Reversão de dividendos e JSCP | C13: 0 | D13: 0 | E13: 911 | F13: 0 | G13: 0 | H13: 911 | I13: 0 | J13: 911
A14: 5.05 | B14: Resultado Abrangente Total | C14: 0 | D14: 0 | E14: 0 | F14: 717513 | G14: 31271 | H14: 748784 | I14: 17930 | J14: 766714
A15: 5.05.01 | B15: Lucro Líquido do Período | C15: 0 | D15: 0 | E15: 0 | F15: 717513 | G15: 0 | H15: 717513 | I15: 17930 | J15: 735443
A16: 5.05.02 | B16: Outros Resultados Abrangentes | C16: 0 | D16: 0 | E16: 0 | F16: 0 | G16: 31271 | H16: 31271 | I16: 0 | J16: 31271
... A21: 5.07 | B21: Saldos Finais | C21: 2962585 | D21: -68362 | E21: 1715436 | F21: 0 | G21: 71693 | H21: 4681352 | I21: 305769 | J21: 4987121

Sheet Ranking_Ativos
A1: Ranking do ativo | Seleção para base simulada
A2: DFP TOTVS S.A. 31/12/2025, versão 1, consolidado (R$ mil)
A4: Código CVM | B4: Rubrica de ativo | C4: Saldo 2025 (R$ mil) | D4: % do ativo | E4: Saldo 2024 (R$ mil) | F4: Variação %
A5: 1.01.01 | B5: Caixa e equivalentes | C5: =BP_Ativo!C7 -> 1785703 | D5: =C5/BP_Ativo!C5 -> 0.18891988 | E5: =BP_Ativo!D7 -> 1942162 | F5: =IF(E5=0,"",C5/E5-1) -> -0.080559191
A6: 1.01.03 | B6: Contas a receber – circulante | C6: =BP_Ativo!C8 -> 639136 | D6: =C6/BP_Ativo!C5 -> 0.067617905 | E6: =BP_Ativo!D8 -> 563328 | F6: =IF(E6=0,"",C6/E6-1) -> 0.13457169
A7: 1.01.06 | B7: Tributos a recuperar | C7: =BP_Ativo!C10 -> 53840 | D7: =C7/BP_Ativo!C5 -> 0.0056960459 | E7: =BP_Ativo!D10 -> 83519 | F7: =IF(E7=0,"",C7/E7-1) -> -0.35535627
A8: 1.01.08 | B8: Outros ativos circulantes | C8: =BP_Ativo!C12 -> 1397091 | D8: =C8/BP_Ativo!C5 -> 0.14780636 | E8: =BP_Ativo!D12 -> 174549 | F8: =IF(E8=0,"",C8/E8-1) -> 7.0040046
A9: 1.02.01 | B9: Realizável a longo prazo | C9: =BP_Ativo!C16 -> 828204 | D9: =C9/BP_Ativo!C5 -> 0.087620505 | E9: =BP_Ativo!D16 -> 785927 | F9: =IF(E9=0,"",C9/E9-1) -> 0.053792528
A10: 1.02.02 | B10: Investimentos | C10: =BP_Ativo!C21 -> 290754 | D10: =C10/BP_Ativo!C5 -> 0.030760552 | E10: =BP_Ativo!D21 -> 321796 | F10: =IF(E10=0,"",C10/E10-1) -> -0.096464841
A11: 1.02.03 | B11: Imobilizado | C11: =BP_Ativo!C23 -> 553190 | D11: =C11/BP_Ativo!C5 -> 0.058525179 | E11: =BP_Ativo!D23 -> 399215 | F11: =IF(E11=0,"",C11/E11-1) -> 0.38569443
A12: 1.02.04 | B12: Intangível (inclui goodwill) | C12: =BP_Ativo!C26 -> 3904253 | D12: =C12/BP_Ativo!C5 -> 0.41305357 | E12: =BP_Ativo!D26 -> 4261225 | F12: =IF(E12=0,"",C12/E12-1) -> -0.083772155
A13: CONFERÊNCIA | B13: Soma das rubricas / total ativo | C13: =SUM(C5:C12)-BP_Ativo!C5 -> 0 | D13: =SUM(D5:D12) -> 1
A15: CANDIDATA À BASE | B15: Intangível: R$ 3.904.253 mil
A16: COMPOSIÇÃO | B16: Goodwill R$ 3.167.139 mil + demais intangíveis R$ 737.114 mil

Sheet Indicadores
A1: Indicadores financeiros | Análise inicial
A2: DFP TOTVS S.A. 31/12/2025, versão 1, consolidado (R$ mil)
A4: Indicador | B4: Cálculo | C4: 2025 | D4: 2024 | E4: Interpretação / referência
A5: Liquidez corrente | B5: Ativo circulante / Passivo circulante | C5: =BP_Ativo!C6/BP_Passivo!C6 -> 1.9592189 | D5: =BP_Ativo!D6/BP_Passivo!D6 -> 2.4152816 | E5: Cálculo a partir da DFP consolidada
A6: Endividamento (Passivo / Ativo) | B6: (PC + PNC) / Ativo total | C6: =(BP_Passivo!C6+BP_Passivo!C25)/BP_Passivo!C25 -> 1.9742575 | D6: =(BP_Passivo!D6+BP_Passivo!D25)/BP_Passivo!D25 -> 1.4766687 | E6: Cálculo a partir da DFP consolidada
A7: Margem líquida consolidada | B7: Lucro consolidado / Receita | C7: =DRE!C32/DRE!C5 -> 0.15952239 | D7: =DRE!D32/DRE!D5 -> 0.14964005 | E7: Cálculo a partir da DFP consolidada
A8: Margem operacional | B8: Resultado antes financeiro / Receita | C8: =DRE!C18/DRE!C5 -> 0.1945173 | D8: =DRE!D18/DRE!D5 -> 0.17335236 | E8: Cálculo a partir da DFP consolidada
A9: Caixa operacional / Receita | B9: Caixa operacional / Receita | C9: =DFC!C5/DRE!C5 -> 0.20845647 | D9: =DFC!D5/DRE!D5 -> 0.21018071 | E9: Cálculo a partir da DFP consolidada
A10: Intangível / Ativo | B10: Intangível / Ativo total | C10: =BP_Ativo!C26/BP_Ativo!C5 -> 0.41305357 | D10: =BP_Ativo!D26/BP_Ativo!D5 -> 0.49945667 | E10: Cálculo a partir da DFP consolidada

Sheet Materialidade
A1: PT 320 | Modelo para definir materialidade (não validado)
A2: DFP TOTVS S.A. 31/12/2025, versão 1, consolidado (R$ mil)
A4: Parâmetro | B4: Valor / fórmula | C4: Observação
A5: Lucro antes dos tributos – 2025 | B5: =DRE!C22 -> 1041978 | C5: Potencial base; confirmar adequação no PT 320
A6: Receita líquida – 2025 | B6: =DRE!C5 -> 5771867 | C6: Base alternativa
A7: Ativo total – 2025 | B7: =BP_Ativo!C5 -> 9452171 | C7: Base alternativa
A8: Base escolhida | B8: =B5 -> 1041978 | C8: Indique a base após justificar os usuários e riscos
A9: Percentual escolhido | B9: 0.05 | C9: Insira o percentual tecnicamente justificado
A10: Materialidade global | B10: =IF(OR(B8="",B9=""),"",B8*B9) -> 52098.9 | C10: Produto da base pelo percentual
A11: Percentual para execução | B11: 0.7 | C11: Justifique com risco e julgamento profissional
A12: Materialidade para execução | B12: =IF(OR(B10="",B11=""),"",B10*B11) -> 36469.23 | C12: Cálculo referencial
A13: Limite trivial | B13: 0.05 | C13: Critério definido com justificativa
A14: Limite claramente trivial | B14: =IF(OR(B10="",B13=""),"",B10*B13) -> 2604.945 | C14: Cálculo referencial

Sheet Fontes_Notas
A1: Fontes e regras | Rastreabilidade
A2: DFP TOTVS S.A. 31/12/2025, versão 1, consolidado (R$ mil)
A4: Campo | B4: Conteúdo
A5: Companhia | B5: TOTVS S.A. — TOTS3
A6: Data-base | B6: 31/12/2025
A7: Base | B7: Demonstrações consolidadas; comparativo 2024
A8: Unidade | B8: Milhares de reais (R$ mil); não converter silenciosamente em reais
A9: DFP | B9: Versão 1
A10: BP Ativo | B10: Páginas internas 1–2 (páginas 2–3 do PDF)
A11: BP Passivo | B11: Páginas internas 3–5 (páginas 4–6 do PDF)
A12: DRE | B12: Páginas internas 6–7 (páginas 7–8 do PDF)
A13: DRA | B13: Página interna 8 (página 9 do PDF)
A14: DFC | B14: Páginas internas 9–10 (páginas 10–11 do PDF)
A15: DMPL | B15: Páginas internas 11–12 (páginas 12–13 do PDF)
... A19: Próxima tarefa | B19: Analisar nota de intangível e definir unidades analíticas sintéticas válidas.
