Workbook

Sheet Bases e premissas
A1: PT-320 | Bases financeiras e premissas | TOTVS S.A. 2025
A3: Indicador | B3: R$ mil | C3: Origem / justificativa | D3: Observação
A4: Lucro antes IR/CSLL (continuadas) | B4: 1041978 | C4: DFP 2025, DRE consolidada; resultado antes IR/CSLL | D4: Base principal proposta
A5: Receita líquida consolidada | B5: 5771867 | C5: DFP 2025, DRE consolidada | D5: Referência de razoabilidade
A6: Ativo total consolidado | B6: 9452171 | C6: DFP 2025, Balanço consolidado | D6: Referência de razoabilidade
A7: Patrimônio líquido consolidado | B7: 5443457 | C7: DFP 2025, Balanço consolidado (inclui não controladores) | D7: Conferir contra DFP ao usar
A8: Intangível consolidado | B8: 3904253 | C8: DFP 2025, balanço e nota de intangíveis | D8: Conta prioritária, não base automática
A9: Goodwill consolidado | B9: 3167139 | C9: DFP 2025, balanço e nota de intangíveis | D9: Subgrupo do intangível
A10: Lucro líquido consolidado | B10: 920742 | C10: DFP 2025, DRE consolidada | D10: Referência contextual
A12: Premissa | B12: Valor | C12: Justificativa acadêmica | D12: Observação
A13: Percentual global | B13: 0.05 | C13: 5% sobre lucro antes de tributos; julgamento profissional | D13: Não é percentual fixado pela NBC TA 320
A14: Fração para execução | B14: 0.7 | C14: 70% da global: margem para distorções agregadas | D14: Não é percentual fixado pela NBC TA 320
A15: Percentual opcional específico | B15: 0.02 | C15: Simulação de 2% do saldo de intangíveis | D15: Não adotado automaticamente
A16: Adotar materialidade específica? | B16: 0 | C16: 0=não, 1=sim; depende de justificativa | D16: Analisar necessidades dos usuários
A17: Unidade dos valores de entrada | B17: 1000 | C17: Valores financeiros da DFP estão em milhares de reais | D17: Resultados em reais na aba de cálculo

Sheet Cálculos PT-320
A1: PT-320 | Memória de cálculo da materialidade
A3: Métrica | B3: Valor em R$ | C3: Cálculo / referência | D3: Tratamento
A4: Base principal escolhida | B4: ='Bases e premissas'!B4*'Bases e premissas'!B17 -> 1041978000 | C4: Lucro antes dos tributos das operações continuadas | D4: Valores em reais
A5: Percentual da materialidade global | B5: ='Bases e premissas'!B13 -> 0.05 | C5: Premissa justificada no papel PT-320 | D5: Percentual
A6: MATERIALIDADE GLOBAL | B6: =B4*B5 -> 52098900 | C6: Base principal x percentual | D6: MG
A7: Percentual para execução | B7: ='Bases e premissas'!B14 -> 0.7 | C7: Premissa justificada no papel PT-320 | D7: Percentual
A8: MATERIALIDADE PARA EXECUÇÃO | B8: =B6*B7 -> 36469230 | C8: MG x fração para execução | D8: ME
A9: Margem entre global e execução | B9: =B6-B8 -> 15629670 | C9: MG menos ME | D9: Diferença
A10: Limite específico ilustrativo (intangível) | B10: ='Bases e premissas'!B8*'Bases e premissas'!B17*'Bases e premissas'!B15 -> 78085060 | C10: Saldo do intangível x 2%; apenas cenário | D10: Não adotado automaticamente
A11: Específica efetivamente adotada | B11: =IF('Bases e premissas'!B16=1,B10,0) -> 0 | C11: Somente se indicação e fundamentação formal | D11: Sem escolha automática
A13: Base alternativa | B13: Valor-base em R$ | C13: Percentual ilustrativo | D13: Materialidade resultante (R$)
A14: Receita líquida | B14: ='Bases e premissas'!B5*'Bases e premissas'!B17 -> 5771867000 | C14: 0.01 | D14: =B14*C14 -> 57718670
A15: Ativo total | B15: ='Bases e premissas'!B6*'Bases e premissas'!B17 -> 9452171000 | C15: 0.005 | D15: =B15*C15 -> 47260855
A16: Patrimônio líquido | B16: ='Bases e premissas'!B7*'Bases e premissas'!B17 -> 5443457000 | C16: 0.01 | D16: =B16*C16 -> 54434570
A19: Nota: comparações são testes de razoabilidade, não critérios normativos automáticos; materialidades específicas exigem justificativa própria.

Sheet Sensibilidade
A1: PT-320 | Sensibilidade e coerência das premissas
A3: % sobre lucro antes IR | B3: Materialidade global (R$) | C3: Execução 60% (R$) | D3: Execução 70% (R$) | E3: Execução 80% (R$)
A4: 0.03 | B4: ='Bases e premissas'!B4*'Bases e premissas'!B17*A4 -> 31259340 | C4: =B4*0.6 -> 18755604 | D4: =B4*0.7 -> 21881538 | E4: =B4*0.8 -> 25007472
A5: 0.04 | B5: ='Bases e premissas'!B4*'Bases e premissas'!B17*A5 -> 41679120 | C5: =B5*0.6 -> 25007472 | D5: =B5*0.7 -> 29175384 | E5: =B5*0.8 -> 33343296
A6: 0.05 | B6: ='Bases e premissas'!B4*'Bases e premissas'!B17*A6 -> 52098900 | C6: =B6*0.6 -> 31259340 | D6: =B6*0.7 -> 36469230 | E6: =B6*0.8 -> 41679120
A7: 0.06 | B7: ='Bases e premissas'!B4*'Bases e premissas'!B17*A7 -> 62518680 | C7: =B7*0.6 -> 37511208 | D7: =B7*0.7 -> 43763076 | E7: =B7*0.8 -> 50014944
A8: 0.07 | B8: ='Bases e premissas'!B4*'Bases e premissas'!B17*A8 -> 72938460 | C8: =B8*0.6 -> 43763076 | D8: =B8*0.7 -> 51056922 | E8: =B8*0.8 -> 58350768
A10: Teste complementar | B10: Resultado | C10: Interpretação
A11: Intangíveis / Ativo total | B11: ='Bases e premissas'!B8/'Bases e premissas'!B6 -> 0.41305357 | C11: Representatividade da conta selecionada.
A12: Global / lucro líquido | B12: ='Cálculos PT-320'!B6/('Bases e premissas'!B10*'Bases e premissas'!B17) -> 0.056583603 | C12: Verificação complementar do porte relativo do limite.

Sheet Fontes e revisões
A1: PT-320 | Evidências, documentação e controle de revisão
A3: Código | B3: Fonte | C3: Informação / uso | D3: Situação
A4: DOC-01 | B4: DFP 2025 TOTVS | C4: BP e DRE consolidados; números da base | D4: Fonte pública
A5: DOC-02 | B5: Notas explicativas 2025 | C5: Intangíveis, goodwill e premissas | D5: Fonte pública
A6: DOC-03 | B6: Relatório dos auditores 2025 | C6: Contexto dos principais assuntos de auditoria | D6: Fonte pública
A7: NOR-320 | B7: NBC TA 320 (R1) | C7: Itens 10–14: MG, execução, revisão e documentação | D7: Referência normativa
A8: PT-315 | B8: Riscos e afirmações | C8: Justificativa e reavaliação dos limites | D8: Referência cruzada
A9: PT-300 | B9: Planejamento da auditoria | C9: Uso de limites no escopo e extensão dos testes | D9: Referência cruzada
A12: Versão | B12: Data | C12: Responsável / matrícula | D12: Alterações | E12: Revisão
A13: 1.0 | B13: 23/10/2026 | C13: Preparador do PT-320 | D13: Criação da memória de cálculo com referências e fórmulas | E13: Pendente – campo reservado
