Workbook

Sheet Premissas
A1: PT-520 | PREMISSAS ACADÊMICAS
A3: Premissa | B3: Valor | C3: Critério | D3: Nota
A4: Materialidade global (R$ mil) | B4: 52098.9 | C4: PT-320 | D4: 5% do lucro pré-tributos 2025
A5: Materialidade execução (R$ mil) | B5: 36469.23 | C5: PT-320 | D5: 70% da materialidade global
A6: Limite percentual - risco ALTO | B6: 0.02 | C6: Acadêmico ilustrativo | D6: Não é limite NBC TA 520
A7: Limite percentual - risco MÉDIO | B7: 0.05 | C7: Acadêmico ilustrativo | D7: Não é limite NBC TA 520
A8: Teto em % da materialidade execução - ALTO | B8: 0.1 | C8: Acadêmico ilustrativo | D8: Teto R$ mil
A9: Teto em % da materialidade execução - MÉDIO | B9: 0.2 | C9: Acadêmico ilustrativo | D9: Teto R$ mil
A10: Modelo de expectativa | B10: Crescimento histórico 2024/2023 aplicado a 2024 | C10: Modelo acadêmico ex ante | D10: Sensível a quebras estruturais e operações descontinuadas
A11: Data base | B11: 31/12/2025 | C11: DFP consolidada | D11: Valores em R$ mil

Sheet Dados_DFP
A1: PT-520 | DFP CONSOLIDADA · R$ MIL
A3: Conta / indicador | B3: 2023 | C3: 2024 | D3: 2025 | E3: Risco / afirmação | F3: Prioridade
A4: Receita líquida | B4: 4180368 | C4: 4914747 | D4: 5771867 | E4: Receita / corte | F4: ALTO
A5: Custos de serviços | B5: 1205006 | C5: 1458672 | D5: 1716326 | E5: Receita / custos | F5: ALTO
A6: Lucro bruto | B6: 2975362 | C6: 3456075 | D6: 4055541 | E6: Margens / receita | F6: ALTO
A7: Resultado operacional antes financeiro | B7: 675111 | C7: 851983 | D7: 1122728 | E7: Estimativas / despesas | F7: ALTO
A8: Lucro antes de tributos | B8: 591478 | C8: 759433 | D8: 1041978 | E8: Resultado / materialidade | F8: ALTO
A9: Lucro líquido consolidado | B9: 764435 | C9: 735443 | D9: 920742 | E9: Desempenho (descontinuadas) | F9: ALTO
A10: Caixa e equivalentes | B10: 3129162 | C10: 1942162 | D10: 1785703 | E10: Liquidez / disponibilidade | F10: MÉDIO
A11: Contas a receber circulantes (líquidas) | B11: 538528 | C11: 563328 | D11: 639136 | E11: Receitas / perdas esperadas | F11: ALTO
A12: Ativo circulante | B12: 3906298 | C12: 2763558 | D12: 3875770 | E12: Liquidez / classificação | F12: MÉDIO
A13: Passivo circulante | B13: 1348729 | C13: 1144197 | D13: 1978222 | E13: Liquidez / integridade | F13: MÉDIO
A14: Ativo total | B14: 8828860 | C14: 8531721 | D14: 9452171 | E14: Apresentação / classificação | F14: MÉDIO
A15: Imobilizado | B15: 413486 | C15: 399215 | D15: 553190 | E15: Existência / mensuração | F15: MÉDIO
... A21: Fornecedores circulantes | B21: 155266 | C21: 211971 | D21: 220761 | E21: Integridade / corte | F21: MÉDIO

Sheet Análises
A1: PT-520 | EXPECTATIVAS, PRECISÃO E INVESTIGAÇÕES
A3: Conta | B3: 2023 | C3: 2024 | D3: 2025 observado | E3: Var. 24/23 | F3: Var. 25/24 | G3: Expectativa 2025 | H3: Desvio R$ mil | I3: Desvio % | J3: Limite R$ mil | K3: Triagem | L3: Investigação / conclusão
A4: =Dados_DFP!A4 -> Receita líquida | B4: =Dados_DFP!B4 -> 4180368 | C4: =Dados_DFP!C4 -> 4914747 | D4: =Dados_DFP!D4 -> 5771867 | E4: =IF(B4=0,"",C4/B4-1) -> 0.17567329 | F4: =IF(C4=0,"",D4/C4-1) -> 0.17439758 | G4: =IF(B4=0,C4,C4*(C4/B4)) -> 5778136.8 | H4: =D4-G4 -> -6269.775 | I4: =IF(G4=0,"",H4/G4) -> -0.001085086 | J4: =MIN(ABS(G4)*IF(Dados_DFP!F4="ALTO",Premissas!$B$6,Premissas!$B$7),Premissas!$B$5*IF(Dados_DFP!F4="ALTO",Premissas!$B$8,Premissas!$B$9)) -> 3646.923 | K4: =IF(ABS(H4)>J4,"INVESTIGAR","DENTRO DO LIMITE") -> INVESTIGAR | L4: Diferença a investigar documentalmente; variação não comprova distorção.
A5: =Dados_DFP!A5 -> Custos de serviços | B5: =Dados_DFP!B5 -> 1205006 | C5: =Dados_DFP!C5 -> 1458672 | D5: =Dados_DFP!D5 -> 1716326 | E5: =IF(B5=0,"",C5/B5-1) -> 0.21051016 | F5: =IF(C5=0,"",D5/C5-1) -> 0.17663601 | G5: =IF(B5=0,C5,C5*(C5/B5)) -> 1765737.3 | H5: =D5-G5 -> -49411.269 | I5: =IF(G5=0,"",H5/G5) -> -0.027983364 | J5: =MIN(ABS(G5)*IF(Dados_DFP!F5="ALTO",Premissas!$B$6,Premissas!$B$7),Premissas!$B$5*IF(Dados_DFP!F5="ALTO",Premissas!$B$8,Premissas!$B$9)) -> 3646.923 | K5: =IF(ABS(H5)>J5,"INVESTIGAR","DENTRO DO LIMITE") -> INVESTIGAR | L5: Diferença a investigar documentalmente; variação não comprova distorção.
A6: =Dados_DFP!A6 -> Lucro bruto | B6: =Dados_DFP!B6 -> 2975362 | C6: =Dados_DFP!C6 -> 3456075 | D6: =Dados_DFP!D6 -> 4055541 | E6: =IF(B6=0,"",C6/B6-1) -> 0.16156454 | F6: =IF(C6=0,"",D6/C6-1) -> 0.17345283 | G6: =IF(B6=0,C6,C6*(C6/B6)) -> 4014454.2 | H6: =D6-G6 -> 41086.824 | I6: =IF(G6=0,"",H6/G6) -> 0.010234722 | J6: =MIN(ABS(G6)*IF(Dados_DFP!F6="ALTO",Premissas!$B$6,Premissas!$B$7),Premissas!$B$5*IF(Dados_DFP!F6="ALTO",Premissas!$B$8,Premissas!$B$9)) -> 3646.923 | K6: =IF(ABS(H6)>J6,"INVESTIGAR","DENTRO DO LIMITE") -> INVESTIGAR | L6: Diferença a investigar documentalmente; variação não comprova distorção.
A7: =Dados_DFP!A7 -> Resultado operacional antes financeiro | B7: =Dados_DFP!B7 -> 675111 | C7: =Dados_DFP!C7 -> 851983 | D7: =Dados_DFP!D7 -> 1122728 | E7: =IF(B7=0,"",C7/B7-1) -> 0.26198951 | F7: =IF(C7=0,"",D7/C7-1) -> 0.31778216 | G7: =IF(B7=0,C7,C7*(C7/B7)) -> 1075193.6 | H7: =D7-G7 -> 47534.391 | I7: =IF(G7=0,"",H7/G7) -> 0.044210076 | J7: =MIN(ABS(G7)*IF(Dados_DFP!F7="ALTO",Premissas!$B$6,Premissas!$B$7),Premissas!$B$5*IF(Dados_DFP!F7="ALTO",Premissas!$B$8,Premissas!$B$9)) -> 3646.923 | K7: =IF(ABS(H7)>J7,"INVESTIGAR","DENTRO DO LIMITE") -> INVESTIGAR | L7: Diferença a investigar documentalmente; variação não comprova distorção.
A8: =Dados_DFP!A8 -> Lucro antes de tributos | B8: =Dados_DFP!B8 -> 591478 | C8: =Dados_DFP!C8 -> 759433 | D8: =Dados_DFP!D8 -> 1041978 | E8: =IF(B8=0,"",C8/B8-1) -> 0.28395815 | F8: =IF(C8=0,"",D8/C8-1) -> 0.3720473 | G8: =IF(B8=0,C8,C8*(C8/B8)) -> 975080.19 | H8: =D8-G8 -> 66897.809 | I8: =IF(G8=0,"",H8/G8) -> 0.068607494 | J8: =MIN(ABS(G8)*IF(Dados_DFP!F8="ALTO",Premissas!$B$6,Premissas!$B$7),Premissas!$B$5*IF(Dados_DFP!F8="ALTO",Premissas!$B$8,Premissas!$B$9)) -> 3646.923 | K8: =IF(ABS(H8)>J8,"INVESTIGAR","DENTRO DO LIMITE") -> INVESTIGAR | L8: Diferença a investigar documentalmente; variação não comprova distorção.
A9: =Dados_DFP!A9 -> Lucro líquido consolidado | B9: =Dados_DFP!B9 -> 764435 | C9: =Dados_DFP!C9 -> 735443 | D9: =Dados_DFP!D9 -> 920742 | E9: =IF(B9=0,"",C9/B9-1) -> -0.03792605 | F9: =IF(C9=0,"",D9/C9-1) -> 0.25195562 | G9: =IF(B9=0,C9,C9*(C9/B9)) -> 707550.55 | H9: =D9-G9 -> 213191.45 | I9: =IF(G9=0,"",H9/G9) -> 0.30130914 | J9: =MIN(ABS(G9)*IF(Dados_DFP!F9="ALTO",Premissas!$B$6,Premissas!$B$7),Premissas!$B$5*IF(Dados_DFP!F9="ALTO",Premissas!$B$8,Premissas!$B$9)) -> 3646.923 | K9: =IF(ABS(H9)>J9,"INVESTIGAR","DENTRO DO LIMITE") -> INVESTIGAR | L9: Diferença a investigar documentalmente; variação não comprova distorção.
A10: =Dados_DFP!A10 -> Caixa e equivalentes | B10: =Dados_DFP!B10 -> 3129162 | C10: =Dados_DFP!C10 -> 1942162 | D10: =Dados_DFP!D10 -> 1785703 | E10: =IF(B10=0,"",C10/B10-1) -> -0.37933479 | F10: =IF(C10=0,"",D10/C10-1) -> -0.080559191 | G10: =IF(B10=0,C10,C10*(C10/B10)) -> 1205432.4 | H10: =D10-G10 -> 580270.61 | I10: =IF(G10=0,"",H10/G10) -> 0.48137964 | J10: =MIN(ABS(G10)*IF(Dados_DFP!F10="ALTO",Premissas!$B$6,Premissas!$B$7),Premissas!$B$5*IF(Dados_DFP!F10="ALTO",Premissas!$B$8,Premissas!$B$9)) -> 7293.846 | K10: =IF(ABS(H10)>J10,"INVESTIGAR","DENTRO DO LIMITE") -> INVESTIGAR | L10: Diferença a investigar documentalmente; variação não comprova distorção.
A11: =Dados_DFP!A11 -> Contas a receber circulantes (líquidas) | B11: =Dados_DFP!B11 -> 538528 | C11: =Dados_DFP!C11 -> 563328 | D11: =Dados_DFP!D11 -> 639136 | E11: =IF(B11=0,"",C11/B11-1) -> 0.046051459 | F11: =IF(C11=0,"",D11/C11-1) -> 0.13457169 | G11: =IF(B11=0,C11,C11*(C11/B11)) -> 589270.08 | H11: =D11-G11 -> 49865.924 | I11: =IF(G11=0,"",H11/G11) -> 0.084623207 | J11: =MIN(ABS(G11)*IF(Dados_DFP!F11="ALTO",Premissas!$B$6,Premissas!$B$7),Premissas!$B$5*IF(Dados_DFP!F11="ALTO",Premissas!$B$8,Premissas!$B$9)) -> 3646.923 | K11: =IF(ABS(H11)>J11,"INVESTIGAR","DENTRO DO LIMITE") -> INVESTIGAR | L11: Diferença a investigar documentalmente; variação não comprova distorção.
A12: =Dados_DFP!A12 -> Ativo circulante | B12: =Dados_DFP!B12 -> 3906298 | C12: =Dados_DFP!C12 -> 2763558 | D12: =Dados_DFP!D12 -> 3875770 | E12: =IF(B12=0,"",C12/B12-1) -> -0.29253785 | F12: =IF(C12=0,"",D12/C12-1) -> 0.40245654 | G12: =IF(B12=0,C12,C12*(C12/B12)) -> 1955112.7 | H12: =D12-G12 -> 1920657.3 | I12: =IF(G12=0,"",H12/G12) -> 0.98237677 | J12: =MIN(ABS(G12)*IF(Dados_DFP!F12="ALTO",Premissas!$B$6,Premissas!$B$7),Premissas!$B$5*IF(Dados_DFP!F12="ALTO",Premissas!$B$8,Premissas!$B$9)) -> 7293.846 | K12: =IF(ABS(H12)>J12,"INVESTIGAR","DENTRO DO LIMITE") -> INVESTIGAR | L12: Diferença a investigar documentalmente; variação não comprova distorção.
A13: =Dados_DFP!A13 -> Passivo circulante | B13: =Dados_DFP!B13 -> 1348729 | C13: =Dados_DFP!C13 -> 1144197 | D13: =Dados_DFP!D13 -> 1978222 | E13: =IF(B13=0,"",C13/B13-1) -> -0.15164796 | F13: =IF(C13=0,"",D13/C13-1) -> 0.72891731 | G13: =IF(B13=0,C13,C13*(C13/B13)) -> 970681.86 | H13: =D13-G13 -> 1007540.1 | I13: =IF(G13=0,"",H13/G13) -> 1.0379715 | J13: =MIN(ABS(G13)*IF(Dados_DFP!F13="ALTO",Premissas!$B$6,Premissas!$B$7),Premissas!$B$5*IF(Dados_DFP!F13="ALTO",Premissas!$B$8,Premissas!$B$9)) -> 7293.846 | K13: =IF(ABS(H13)>J13,"INVESTIGAR","DENTRO DO LIMITE") -> INVESTIGAR | L13: Diferença a investigar documentalmente; variação não comprova distorção.
A14: =Dados_DFP!A14 -> Ativo total | B14: =Dados_DFP!B14 -> 8828860 | C14: =Dados_DFP!C14 -> 8531721 | D14: =Dados_DFP!D14 -> 9452171 | E14: =IF(B14=0,"",C14/B14-1) -> -0.033655421 | F14: =IF(C14=0,"",D14/C14-1) -> 0.10788562 | G14: =IF(B14=0,C14,C14*(C14/B14)) -> 8244582.3 | H14: =D14-G14 -> 1207588.7 | I14: =IF(G14=0,"",H14/G14) -> 0.14647057 | J14: =MIN(ABS(G14)*IF(Dados_DFP!F14="ALTO",Premissas!$B$6,Premissas!$B$7),Premissas!$B$5*IF(Dados_DFP!F14="ALTO",Premissas!$B$8,Premissas!$B$9)) -> 7293.846 | K14: =IF(ABS(H14)>J14,"INVESTIGAR","DENTRO DO LIMITE") -> INVESTIGAR | L14: Diferença a investigar documentalmente; variação não comprova distorção.
A15: =Dados_DFP!A15 -> Imobilizado | B15: =Dados_DFP!B15 -> 413486 | C15: =Dados_DFP!C15 -> 399215 | D15: =Dados_DFP!D15 -> 553190 | E15: =IF(B15=0,"",C15/B15-1) -> -0.034513865 | F15: =IF(C15=0,"",D15/C15-1) -> 0.38569443 | G15: =IF(B15=0,C15,C15*(C15/B15)) -> 385436.55 | H15: =D15-G15 -> 167753.45 | I15: =IF(G15=0,"",H15/G15) -> 0.43522975 | J15: =MIN(ABS(G15)*IF(Dados_DFP!F15="ALTO",Premissas!$B$6,Premissas!$B$7),Premissas!$B$5*IF(Dados_DFP!F15="ALTO",Premissas!$B$8,Premissas!$B$9)) -> 7293.846 | K15: =IF(ABS(H15)>J15,"INVESTIGAR","DENTRO DO LIMITE") -> INVESTIGAR | L15: Diferença a investigar documentalmente; variação não comprova distorção.
... A21: =Dados_DFP!A21 -> Fornecedores circulantes | B21: =Dados_DFP!B21 -> 155266 | C21: =Dados_DFP!C21 -> 211971 | D21: =Dados_DFP!D21 -> 220761 | E21: =IF(B21=0,"",C21/B21-1) -> 0.36521196 | F21: =IF(C21=0,"",D21/C21-1) -> 0.041467937 | G21: =IF(B21=0,C21,C21*(C21/B21)) -> 289385.34 | H21: =D21-G21 -> -68624.344 | I21: =IF(G21=0,"",H21/G21) -> -0.23713828 | J21: =MIN(ABS(G21)*IF(Dados_DFP!F21="ALTO",Premissas!$B$6,Premissas!$B$7),Premissas!$B$5*IF(Dados_DFP!F21="ALTO",Premissas!$B$8,Premissas!$B$9)) -> 7293.846 | K21: =IF(ABS(H21)>J21,"INVESTIGAR","DENTRO DO LIMITE") -> INVESTIGAR | L21: Diferença a investigar documentalmente; variação não comprova distorção.

Sheet Indicadores
A1: PT-520 | INDICADORES E RELAÇÕES · CONSOLIDADO
A3: Indicador | B3: 2023 | C3: 2024 | D3: 2025 | E3: Variação 25/24 | F3: Interpretação / limitação
A4: Margem bruta | B4: =IF(Dados_DFP!B4=0,"",Dados_DFP!B6/Dados_DFP!B4) -> 0.71174643 | C4: =IF(Dados_DFP!C4=0,"",Dados_DFP!C6/Dados_DFP!C4) -> 0.70320507 | D4: =IF(Dados_DFP!D4=0,"",Dados_DFP!D6/Dados_DFP!D4) -> 0.70263937 | E4: =IF(C4=0,"",D4/C4-1) -> -0.00080445532 | F4: Razão calculada com dados publicados; requer análise de composição.
A5: Margem operacional | B5: =IF(Dados_DFP!B4=0,"",Dados_DFP!B7/Dados_DFP!B4) -> 0.16149559 | C5: =IF(Dados_DFP!C4=0,"",Dados_DFP!C7/Dados_DFP!C4) -> 0.17335236 | D5: =IF(Dados_DFP!D4=0,"",Dados_DFP!D7/Dados_DFP!D4) -> 0.1945173 | E5: =IF(C5=0,"",D5/C5-1) -> 0.12209202 | F5: Razão calculada com dados publicados; requer análise de composição.
A6: Margem líquida | B6: =IF(Dados_DFP!B4=0,"",Dados_DFP!B9/Dados_DFP!B4) -> 0.18286309 | C6: =IF(Dados_DFP!C4=0,"",Dados_DFP!C9/Dados_DFP!C4) -> 0.14964005 | D6: =IF(Dados_DFP!D4=0,"",Dados_DFP!D9/Dados_DFP!D4) -> 0.15952239 | E6: =IF(C6=0,"",D6/C6-1) -> 0.066040702 | F6: Razão calculada com dados publicados; requer análise de composição.
A7: Liquidez corrente | B7: =IF(Dados_DFP!B13=0,"",Dados_DFP!B12/Dados_DFP!B13) -> 2.8962809 | C7: =IF(Dados_DFP!C13=0,"",Dados_DFP!C12/Dados_DFP!C13) -> 2.4152816 | D7: =IF(Dados_DFP!D13=0,"",Dados_DFP!D12/Dados_DFP!D13) -> 1.9592189 | E7: =IF(C7=0,"",D7/C7-1) -> -0.18882382 | F7: Razão calculada com dados publicados; requer análise de composição.
A8: Contas a receber / receita | B8: =IF(Dados_DFP!B4=0,"",Dados_DFP!B11/Dados_DFP!B4) -> 0.12882311 | C8: =IF(Dados_DFP!C4=0,"",Dados_DFP!C11/Dados_DFP!C4) -> 0.11461994 | D8: =IF(Dados_DFP!D4=0,"",Dados_DFP!D11/Dados_DFP!D4) -> 0.11073297 | E8: =IF(C8=0,"",D8/C8-1) -> -0.033911765 | F8: Razão calculada com dados publicados; requer análise de composição.
A9: Intangível / ativo | B9: =IF(Dados_DFP!B14=0,"",Dados_DFP!B18/Dados_DFP!B14) -> 0.41582118 | C9: =IF(Dados_DFP!C14=0,"",Dados_DFP!C18/Dados_DFP!C14) -> 0.49945667 | D9: =IF(Dados_DFP!D14=0,"",Dados_DFP!D18/Dados_DFP!D14) -> 0.41305357 | E9: =IF(C9=0,"",D9/C9-1) -> -0.17299419 | F9: Razão calculada com dados publicados; requer análise de composição.
A10: Goodwill / ativo | B10: =IF(Dados_DFP!B14=0,"",Dados_DFP!B17/Dados_DFP!B14) -> 0.33440388 | C10: =IF(Dados_DFP!C14=0,"",Dados_DFP!C17/Dados_DFP!C14) -> 0.396379 | D10: =IF(Dados_DFP!D14=0,"",Dados_DFP!D17/Dados_DFP!D14) -> 0.33507001 | E10: =IF(C10=0,"",D10/C10-1) -> -0.15467265 | F10: Razão calculada com dados publicados; requer análise de composição.
A11: Provisões / passivo circulante | B11: =IF(Dados_DFP!B13=0,"",Dados_DFP!B20/Dados_DFP!B13) -> 0.08303373 | C11: =IF(Dados_DFP!C13=0,"",Dados_DFP!C20/Dados_DFP!C13) -> 0.092879111 | D11: =IF(Dados_DFP!D13=0,"",Dados_DFP!D20/Dados_DFP!D13) -> 0.05396917 | E11: =IF(C11=0,"",D11/C11-1) -> -0.41893102 | F11: Razão calculada com dados publicados; requer análise de composição.

Sheet Guia_Fontes
A1: PT-520 | FONTES, METODOLOGIA E LIMITAÇÕES
A3: Ref. | B3: Fonte | C3: Aplicação | D3: Limitação
A4: DOC-01 | B4: DFP TOTVS S.A. 2025, versão 1, Balanço pp. 1–4, DRE p. 6 | C4: Séries consolidadas 2023–2025 | D4: Comparativos 2023–2025 sujeitos a reclassificações/escopo
A5: PT-315 | B5: Identificação e avaliação de riscos | C5: Prioridade ALTO/MÉDIO | D5: Classificações acadêmicas preliminares
A6: PT-320 | B6: Materialidade global R$ 52.098,90 mil; execução R$ 36.469,23 mil | C6: Tetos de triagem | D6: Teto não equivale a distorção tolerável nem critério NBC
A7: PT-330 | B7: Respostas aos riscos | C7: Testes executados/documentais e não executados | D7: Sem documentos internos da TOTVS
A8: PT-500 | B8: Evidência de auditoria | C8: Limites de fontes públicas | D8: Não fornece prova de transações reais
A9: PT-510 | B9: Saldos iniciais | C9: Comparabilidade 2024–2025 | D9: Confrontar reapresentações com DFP 2024 original
A10: MÉTODO | B10: Expectativa=C2024*(C2024/C2023); diferença=real−expectativa | C10: Extrapolação da taxa passada | D10: Extrapolação simplificada; não previsão econômica validada
A11: STATUS | B11: INVESTIGAR quando ABS(desvio)>menor entre % da expectativa e fração da execução | C11: Triagem a priori acadêmica | D11: Sinalização não significa distorção identificada
