Workbook

Sheet Premissas
A1: PT-540 | SIMULAÇÃO ACADÊMICA — UGC RD
A2: Parâmetro | B2: Valor | C2: Origem / ressalva
A3: Goodwill UGC RD (R$ mil) | B3: 1825883 | C3: Nota 15.1, 2025, divulgado; não é valor contábil completo da UGC
A4: Goodwill UGC Gestão (R$ mil) | B4: 1341256 | C4: Nota 15.1, divulgado
A5: Goodwill total (R$ mil) | B5: 3167139 | C5: Nota 15.1, divulgado
A6: Taxa de desconto no modelo | B6: 0.1442 | C6: HIPÓTESE: uma das taxas nominais divulgadas (13,66% e 14,42%); a DFP não identifica qual se aplica à RD
A7: Taxa perpétua de crescimento | B7: 0.056 | C7: Nota 15.2: taxa nominal divulgada de 5,6%
A8: Crescimento dos fluxos explícitos | B8: 0.08 | C8: HIPÓTESE ACADÊMICA, NÃO DIVULGADA
A9: FCF ano 1 (R$ mil) | B9: 300000 | C9: HIPÓTESE ACADÊMICA, NÃO DIVULGADA
A10: Horizonte explícito (anos) | B10: 5 | C10: Hipótese: dentro da faixa de 5–10 anos divulgada
A11: Valor contábil TOTAL da UGC (R$ mil) | B11: 2000000 | C11: VALOR MERAMENTE HIPOTÉTICO; não é saldo real nem somente goodwill
A12: Choque taxa de desconto (p.p.) | B12: 0.01 | C12: Cenários +1 / -1 ponto percentual
A13: Choque crescimento perpetuidade (p.p.) | B13: 0.01 | C13: Cenários +1 / -1 ponto percentual
A14: Choque fluxo de caixa | B14: 0.1 | C14: Cenários -10% / +10%
... A16: Materialidade para execução (R$ mil) | B16: 36469.23 | C16: PT-320

Sheet Fluxos_DCF
A1: FLUXOS DE CAIXA DESCONTADOS — EXERCÍCIO HIPOTÉTICO (R$ MIL)
A3: Indicador | B3: 1 | C3: 2 | D3: 3 | E3: 4 | F3: 5 | G3: Nota
A4: Fluxo nominal | B4: =Premissas!B9 -> 300000 | C4: =B4*(1+Premissas!$B$8) -> 324000 | D4: =C4*(1+Premissas!$B$8) -> 349920 | E4: =D4*(1+Premissas!$B$8) -> 377913.6 | F4: =E4*(1+Premissas!$B$8) -> 408146.69
A5: Fator de desconto | B5: =1/(1+Premissas!$B$6)^1 -> 0.87397308 | C5: =1/(1+Premissas!$B$6)^2 -> 0.76382895 | D5: =1/(1+Premissas!$B$6)^3 -> 0.66756594 | E5: =1/(1+Premissas!$B$6)^4 -> 0.58343466 | F5: =1/(1+Premissas!$B$6)^5 -> 0.50990619
A6: Valor presente | B6: =B4*B5 -> 262191.92 | C6: =C4*C5 -> 247480.58 | D6: =D4*D5 -> 233594.67 | E6: =E4*E5 -> 220487.89 | F6: =F4*F5 -> 208116.52
A9: VP dos fluxos explícitos | B9: =SUM(B6:F6) -> 1171871.6 | D9: A referência para comparação é apenas ilustrativa. Goodwill de R$ 1.825.883 mil NÃO equivale ao valor contábil total da UGC RD. O valor recuperável real não foi fornecido.
A10: Fluxo terminal ano 6 | B10: =F4*(1+Premissas!B7) -> 431002.9
A11: Valor terminal no fim do ano 5 | B11: =B10/(Premissas!B6-Premissas!B7) -> 4886654.2
A12: VP do valor terminal | B12: =B11*F5 -> 2491735.2
A13: Valor em uso ilustrativo | B13: =B9+B12 -> 3663606.8
A14: Valor contábil hipotético da UGC | B14: =Premissas!B11 -> 2000000
A15: Folga hipotética (headroom) | B15: =B13-B14 -> 1663606.8
A16: Perda hipotética se valor em uso fosse recuperável | B16: =MAX(0,B14-B13) -> 0

Sheet Sensibilidade
A1: ANÁLISE DE SENSIBILIDADE DCF | PREMISSAS DIDÁTICAS | VALORES R$ MIL
A3: Cenário | B3: Desconto | C3: Perpetuidade | D3: Multiplicador FCF | E3: VP 5 anos | F3: VP terminal | G3: Valor em uso | H3: Folga vs UGC hipotética
A4: Base | B4: =Premissas!B6 -> 0.1442 | C4: =Premissas!B7 -> 0.056 | D4: =1 -> 1 | E4: =SUMPRODUCT(Fluxos_DCF!$B$4:$F$4,D4/(1+B4)^Fluxos_DCF!$B$3:$F$3) -> 1171871.6 | F4: =(Fluxos_DCF!$F$4*D4*(1+C4)/(B4-C4))/(1+B4)^Premissas!$B$10 -> 2491735.2 | G4: =E4+F4 -> 3663606.8 | H4: =G4-Premissas!$B$11 -> 1663606.8
A5: Desconto +1 pp | B5: =Premissas!B6+Premissas!B12 -> 0.1542 | C5: =Premissas!B7 -> 0.056 | D5: =1 -> 1 | E5: =SUMPRODUCT(Fluxos_DCF!$B$4:$F$4,D5/(1+B5)^Fluxos_DCF!$B$3:$F$3) -> 1142907.8 | F5: =(Fluxos_DCF!$F$4*D5*(1+C5)/(B5-C5))/(1+B5)^Premissas!$B$10 -> 2142709.8 | G5: =E5+F5 -> 3285617.6 | H5: =G5-Premissas!$B$11 -> 1285617.6
A6: Desconto -1 pp | B6: =Premissas!B6-Premissas!B12 -> 0.1342 | C6: =Premissas!B7 -> 0.056 | D6: =1 -> 1 | E6: =SUMPRODUCT(Fluxos_DCF!$B$4:$F$4,D6/(1+B6)^Fluxos_DCF!$B$3:$F$3) -> 1202017 | F6: =(Fluxos_DCF!$F$4*D6*(1+C6)/(B6-C6))/(1+B6)^Premissas!$B$10 -> 2936467.7 | G6: =E6+F6 -> 4138484.7 | H6: =G6-Premissas!$B$11 -> 2138484.7
A7: Perpetuidade -1 pp | B7: =Premissas!B6 -> 0.1442 | C7: =Premissas!B7-Premissas!B13 -> 0.046 | D7: =1 -> 1 | E7: =SUMPRODUCT(Fluxos_DCF!$B$4:$F$4,D7/(1+B7)^Fluxos_DCF!$B$3:$F$3) -> 1171871.6 | F7: =(Fluxos_DCF!$F$4*D7*(1+C7)/(B7-C7))/(1+B7)^Premissas!$B$10 -> 2216801.2 | G7: =E7+F7 -> 3388672.8 | H7: =G7-Premissas!$B$11 -> 1388672.8
A8: Perpetuidade +1 pp | B8: =Premissas!B6 -> 0.1442 | C8: =Premissas!B7+Premissas!B13 -> 0.066 | D8: =1 -> 1 | E8: =SUMPRODUCT(Fluxos_DCF!$B$4:$F$4,D8/(1+B8)^Fluxos_DCF!$B$3:$F$3) -> 1171871.6 | F8: =(Fluxos_DCF!$F$4*D8*(1+C8)/(B8-C8))/(1+B8)^Premissas!$B$10 -> 2836984.8 | G8: =E8+F8 -> 4008856.4 | H8: =G8-Premissas!$B$11 -> 2008856.4
A9: FCF -10% | B9: =Premissas!B6 -> 0.1442 | C9: =Premissas!B7 -> 0.056 | D9: =1-Premissas!B14 -> 0.9 | E9: =SUMPRODUCT(Fluxos_DCF!$B$4:$F$4,D9/(1+B9)^Fluxos_DCF!$B$3:$F$3) -> 1054684.4 | F9: =(Fluxos_DCF!$F$4*D9*(1+C9)/(B9-C9))/(1+B9)^Premissas!$B$10 -> 2242561.7 | G9: =E9+F9 -> 3297246.1 | H9: =G9-Premissas!$B$11 -> 1297246.1
A10: FCF +10% | B10: =Premissas!B6 -> 0.1442 | C10: =Premissas!B7 -> 0.056 | D10: =1+Premissas!B14 -> 1.1 | E10: =SUMPRODUCT(Fluxos_DCF!$B$4:$F$4,D10/(1+B10)^Fluxos_DCF!$B$3:$F$3) -> 1289058.8 | F10: =(Fluxos_DCF!$F$4*D10*(1+C10)/(B10-C10))/(1+B10)^Premissas!$B$10 -> 2740908.8 | G10: =E10+F10 -> 4029967.5 | H10: =G10-Premissas!$B$11 -> 2029967.5
A11: Combinado desfavorável | B11: =Premissas!B6+Premissas!B12 -> 0.1542 | C11: =Premissas!B7-Premissas!B13 -> 0.046 | D11: =1-Premissas!B14 -> 0.9 | E11: =SUMPRODUCT(Fluxos_DCF!$B$4:$F$4,D11/(1+B11)^Fluxos_DCF!$B$3:$F$3) -> 1028617 | F11: =(Fluxos_DCF!$F$4*D11*(1+C11)/(B11-C11))/(1+B11)^Premissas!$B$10 -> 1733635.8 | G11: =E11+F11 -> 2762252.8 | H11: =G11-Premissas!$B$11 -> 762252.79
A13: AVISO: Folga e perdas referem-se a valor contábil total da UGC HIPOTÉTICO. Não se infere perda ou recuperabilidade da TOTVS.

Sheet Fontes_e_Limites
A1: ID | B1: Fonte / dado | C1: Limitação / uso
A2: DOC-01 | B2: DFP consolidada TOTVS 2025, notas 15.1 e 15.2 | C2: Goodwill, prazo 5–10 anos, taxas 13,66% e 14,42% (sem identificação individual de UGC), perpetuidade 5,6%
A3: DOC-02 | B3: Relatório dos auditores independentes de 2025 | C3: Valor recuperável da UGC RD foi principal assunto; não transfere papéis ou testes internos
A4: PT-315 | B4: Avaliação de riscos | C4: Mensuração do goodwill: risco alto e candidato a significativo
A5: PT-320 | B5: Materialidade | C5: Global 52.098,9 R$ mil; execução 36.469,23 R$ mil
A6: PT-330 | B6: Respostas a riscos | C6: Conciliação pública executada; recálculo independente real não executado
A7: SIM-540 | B7: Modelagem hipotética DCF | C7: FCF, crescimento explícito, desconto atribuído à RD e valor contábil total da UGC não foram divulgados
A8: NOR-540 | B8: NBC TA 540 (R2) e CPC 01 | C8: Método, premissas, dados, incerteza, viés; valor recuperável = maior entre VIU e VJ menos despesas
A9: STATUS | B9: 25/10/2026 — preparadora 241021687 | C9: Sem revisão por terceiro e sem acesso a fluxos internos
