Workbook

Sheet Premissas
A1: PT-570 | Premissas e critérios
A3: Parâmetro | B3: Valor | C3: Fundamentação / limite
A4: Data-base | B4: 31/12/2025 | C4: DFP consolidadas TOTVS 2025
A5: Data de análise | B5: 25/10/2026 | C5: Execução acadêmica retrospectiva
A6: Moeda | B6: R$ mil | C6: Demonstrações publicadas; não converter em R$ sem indicação
A7: Materialidade global (R$ mil) | B7: 52098.9 | C7: PT-320 — parâmetro orientador, não gatilho automático
A8: Materialidade execução (R$ mil) | B8: 36469.23 | C8: PT-320
A9: Covenant Dívida líquida / EBITDA ajustado | B9: 4 | C9: Relatório agente fiduciário 5ª emissão — limite máximo
A10: Estresse de queda do FCO | B10: 0.3 | C10: Hipótese didática editável: redução de 30%
A11: Estresse de aumento dos passivos CP | B11: 0.15 | C11: Hipótese didática editável: aumento de 15%
A12: Estresse de queda do caixa | B12: 0.2 | C12: Hipótese didática editável: redução de 20%
A13: Horizonte de análise | B13: 12 meses ou mais | C13: Solicitar projeções da administração; não obtidas
A14: Qualidade de evidência | B14: Documental e parcial | C14: Não substitui fluxo de caixa projetado / escritura integral

Sheet Dados_DFP
A1: PT-570 | Dados publicados das DFPs (R$ mil)
A3: Conta | B3: 2023 | C3: 2024 | D3: 2025 | E3: Origem / referência
A4: Ativo total | B4: 8828860 | C4: 8531721 | D4: 9452171 | E4: DFP BP Ativo
A5: Ativo circulante | B5: 3906298 | C5: 2763558 | D5: 3875770 | E5: DFP BP Ativo
A6: Passivo circulante | B6: 1348729 | C6: 1144197 | D6: 1978222 | E6: DFP BP Passivo
A7: Passivo não circulante | B7: 2467460 | C7: 2400403 | D7: 2030492 | E7: DFP BP Passivo
A8: Patrimônio líquido | B8: 5012671 | C8: 4987121 | D8: 5443457 | E8: DFP BP Passivo
A9: Caixa e equivalentes | B9: 3129162 | C9: 1942162 | D9: 1785703 | E9: DFP BP Ativo
A10: Empréstimos / debêntures / arrendamentos CP | B10: 145909 | C10: 120978 | D10: 142572 | E10: DFP BP Passivo, conta 2.01.04
A11: Empréstimos / debêntures / arrendamentos LP | B11: 1598158 | C11: 1540571 | D11: 1693710 | E11: DFP BP Passivo, conta 2.02.01
A12: Fluxo operacional | B12: 890109 | C12: 1032985 | D12: 1203183 | E12: DFC 6.01
A13: Fluxo investimento | B13: 58016 | C13: -1253473 | D13: -939333 | E13: DFC 6.02
A14: Fluxo financiamento | B14: -554728 | C14: -966512 | D14: -420309 | E14: DFC 6.03
A15: Receita líquida | B15: 4180368 | C15: 4914747 | D15: 5771867 | E15: DRE 3.01
... A21: Intangíveis líquidos | B21: 3671227 | C21: 4261225 | D21: 3904253 | E21: DFP BP Ativo

Sheet Indicadores
A1: PT-570 | Indicadores financeiros (calculados)
A3: Indicador | B3: 2023 | C3: 2024 | D3: 2025 | E3: Definição / ressalva
A4: Liquidez corrente | B4: =Dados_DFP!B5/Dados_DFP!B6 -> 2.8962809 | C4: =Dados_DFP!C5/Dados_DFP!C6 -> 2.4152816 | D4: =Dados_DFP!D5/Dados_DFP!D6 -> 1.9592189 | E4: Ativo circulante / passivo circulante
A5: Capital circulante líquido | B5: =Dados_DFP!B5-Dados_DFP!B6 -> 2557569 | C5: =Dados_DFP!C5-Dados_DFP!C6 -> 1619361 | D5: =Dados_DFP!D5-Dados_DFP!D6 -> 1897548 | E5: Ativo circulante - passivo circulante (R$ mil)
A6: Endividamento geral | B6: =(Dados_DFP!B6+Dados_DFP!B7)/Dados_DFP!B4 -> 0.43224029 | C6: =(Dados_DFP!C6+Dados_DFP!C7)/Dados_DFP!C4 -> 0.41546131 | D6: =(Dados_DFP!D6+Dados_DFP!D7)/Dados_DFP!D4 -> 0.42410511 | E6: Passivos exigíveis / ativo total
A7: Dívida financeira bruta | B7: =Dados_DFP!B10+Dados_DFP!B11 -> 1744067 | C7: =Dados_DFP!C10+Dados_DFP!C11 -> 1661549 | D7: =Dados_DFP!D10+Dados_DFP!D11 -> 1836282 | E7: Empréstimos, debêntures e arrendamentos CP + LP
A8: Dívida financeira líquida simplificada | B8: =B7-Dados_DFP!B9 -> -1385095 | C8: =C7-Dados_DFP!C9 -> -280613 | D8: =D7-Dados_DFP!D9 -> 50579 | E8: Dívida bruta menos caixa (NÃO igual ao covenant)
A9: Fluxo operacional / dívida financeira CP | B9: =Dados_DFP!B12/Dados_DFP!B10 -> 6.1004393 | C9: =Dados_DFP!C12/Dados_DFP!C10 -> 8.5386186 | D9: =Dados_DFP!D12/Dados_DFP!D10 -> 8.4391255 | E9: Proxy de cobertura; FCO anual / dívida CP, sem correspondência temporal perfeita
A10: Resultado operacional / despesa financeira | B10: =Dados_DFP!B16/Dados_DFP!B17 -> 1.8464625 | C10: =Dados_DFP!C16/Dados_DFP!C17 -> 2.7415138 | D10: =Dados_DFP!D16/Dados_DFP!D17 -> 3.2001414 | E10: Proxy não contratual de cobertura (EBIT/despesa financeira)
A11: FCO / receita | B11: =Dados_DFP!B12/Dados_DFP!B15 -> 0.21292599 | C11: =Dados_DFP!C12/Dados_DFP!C15 -> 0.21018071 | D11: =Dados_DFP!D12/Dados_DFP!D15 -> 0.20845647 | E11: Conversão de vendas em fluxo de caixa operacional
A12: Caixa / passivo circulante | B12: =Dados_DFP!B9/Dados_DFP!B6 -> 2.3200821 | C12: =Dados_DFP!C9/Dados_DFP!C6 -> 1.6974018 | D12: =Dados_DFP!D9/Dados_DFP!D6 -> 0.90268079 | E12: Cobertura imediata simplificada
A13: FCO / fluxo investimento absoluto | B13: =Dados_DFP!B12/ABS(Dados_DFP!B13) -> 15.342474 | C13: =Dados_DFP!C12/ABS(Dados_DFP!C13) -> 0.82409833 | D13: =Dados_DFP!D12/ABS(Dados_DFP!D13) -> 1.2808908 | E13: Não presume que todos os investimentos são recorrentes

Sheet Covenants
A1: PT-570 | Verificação documental do covenant
A3: Item | B3: 30/06/2025 | C3: 30/12/2025 | D3: Fonte / interpretação
A4: Dívida líquida / EBITDA ajustado | B4: -0.19 | C4: -0.01 | D4: Agente fiduciário 2025, p. 2; índice CONTRATUAL
A5: Limite máximo | B5: 4 | C5: 4 | D5: Agente fiduciário 2025, p. 2
A6: Folga em pontos de múltiplo | B6: =B5-B4 -> 4.19 | C6: =C5-C4 -> 4.01 | D6: Limite menos índice; não reflete headroom monetário
A7: Resultado informado | B7: Ok | C7: Ok | D7: Agente fiduciário, p. 2; não é teste independente
A8: Vencimento | B8: 19/07/2031 | C8: 19/07/2031 | D8: 5ª emissão, p. 1
A9: Primeira amortização principal | B9: 19/07/2028 | C9: 19/07/2028 | D9: 5ª emissão, p. 2
A10: Remuneração | B10: CDI + 0,95% a.a. | C10: CDI + 0,95% a.a. | D10: 5ª emissão, p. 2
A11: Escritura / memória de cálculo | B11: Não recebida | C11: Não recebida | D11: Pendente para reexecutar covenant

Sheet Cenários
A1: PT-570 | Estresse estático didático — NÃO é previsão de caixa
A3: Cenário | B3: Caixa (R$ mil) | C3: Passivo CP (R$ mil) | D3: FCO anual (R$ mil) | E3: Liquidez corrente | F3: Caixa / PC | G3: FCO / PC | H3: Natureza
A4: Base em 31/12/2025 | B4: =Dados_DFP!D9 -> 1785703 | C4: =Dados_DFP!D6 -> 1978222 | D4: =Dados_DFP!D12 -> 1203183 | E4: =Dados_DFP!D5/Dados_DFP!D6 -> 1.9592189 | F4: =Dados_DFP!D9/Dados_DFP!D6 -> 0.90268079 | G4: =Dados_DFP!D12/Dados_DFP!D6 -> 0.60821435 | H4: Dados DFP 2025
A5: Queda do caixa | B5: =Dados_DFP!D9*(1-Premissas!B12) -> 1428562.4 | C5: =Dados_DFP!D6 -> 1978222 | D5: =Dados_DFP!D12 -> 1203183 | E5: =Dados_DFP!D5/Dados_DFP!D6 -> 1.9592189 | F5: =Dados_DFP!D9*(1-Premissas!B12)/Dados_DFP!D6 -> 0.72214463 | G5: =Dados_DFP!D12/Dados_DFP!D6 -> 0.60821435 | H5: Redução de 20% do caixa; demais valores constantes
A6: Aumento do passivo CP | B6: =Dados_DFP!D9 -> 1785703 | C6: =Dados_DFP!D6*(1+Premissas!B11) -> 2274955.3 | D6: =Dados_DFP!D12 -> 1203183 | E6: =Dados_DFP!D5/Dados_DFP!D6*(1+Premissas!B11) -> 2.2531018 | F6: =Dados_DFP!D9/Dados_DFP!D6*(1+Premissas!B11) -> 1.0380829 | G6: =Dados_DFP!D12/Dados_DFP!D6*(1+Premissas!B11) -> 0.6994465 | H6: Aumento de 15% do passivo; demais constantes
A7: Queda FCO | B7: =Dados_DFP!D9 -> 1785703 | C7: =Dados_DFP!D6 -> 1978222 | D7: =Dados_DFP!D12*(1-Premissas!B10) -> 842228.1 | E7: =Dados_DFP!D5/Dados_DFP!D6 -> 1.9592189 | F7: =Dados_DFP!D9/Dados_DFP!D6 -> 0.90268079 | G7: =Dados_DFP!D12*(1-Premissas!B10)/Dados_DFP!D6 -> 0.42575004 | H7: Redução de 30% do FCO; não projeta tempo / sazonalidade
A8: Combinado | B8: =Dados_DFP!D9*(1-Premissas!B12) -> 1428562.4 | C8: =Dados_DFP!D6*(1+Premissas!B11) -> 2274955.3 | D8: =Dados_DFP!D12*(1-Premissas!B10) -> 842228.1 | E8: =Dados_DFP!D5/Dados_DFP!D6*(1+Premissas!B11) -> 2.2531018 | F8: =Dados_DFP!D9*(1-Premissas!B12)/Dados_DFP!D6*(1+Premissas!B11) -> 0.83046633 | G8: =Dados_DFP!D12*(1-Premissas!B10)/Dados_DFP!D6*(1+Premissas!B11) -> 0.48961255 | H8: Três choques simultâneos; só ilustração

Sheet Fontes_Limites
A1: PT-570 | Fontes, cautelas e reprodução
A3: Ref. | B3: Fonte / item | C3: Interpretação e limitações
A4: DOC-01 | B4: DFP consolidadas TOTVS 2025 | C4: Balanço, DRE, DFC comparativos 2023–2025. Valores em R$ mil.
A5: DOC-02 | B5: Notas às DFP 2025 e relatório auditor | C5: Divulgações de dívida, liquidez, riscos e continuidade.
A6: DOC-03 | B6: Relatório Oliveira Trust — 5ª emissão 2025, pp.1–4 | C6: Condições, pagamentos e índice do covenant; cálculo do agente baseado em informações da emissora.
A7: DOC-04 | B7: Fato Relevante 6ª emissão, 06/01/2026 | C7: Captação aprovada de R$ 3 bi, após data-base; não confundir aprovação com ingresso em caixa em 2025.
A8: DOC-05 | B8: Fato Relevante Dimensa, 02/02/2026 | C8: Contrato de venda, fechamento condicional; não projetar recebimento sem comprovação.
A9: PT-520 | B9: Procedimentos analíticos | C9: Indicadores históricos contextualizam oscilações, mas não são projeção.
A10: PT-560 | B10: Eventos subsequentes | C10: Marcos temporais e impactos potenciais da 6ª emissão / Dimensa.
A11: PT-320 | B11: Materialidade | C11: R$ 52.098,9 mil global; R$ 36.469,23 mil para execução.
A12: LIMITAÇÃO | B12: Projeções e covenants completos ausentes | C12: Não é possível concluir independentemente se existe ou não incerteza relevante sobre continuidade.
A13: REPRODUÇÃO | B13: Células com fórmulas nas abas Indicadores, Covenants e Cenarios | C13: Células com dados publicados em Dados_DFP e hipóteses acadêmicas em Premissas.
